sanysdk/__init__.py
sanysdk/sanysdk.py
sanysdk-0.0.4.dist-info/LICENSE
sanysdk-0.0.4.dist-info/METADATA
sanysdk-0.0.4.dist-info/WHEEL
sanysdk-0.0.4.dist-info/top_level.txt
sanysdk-0.0.4.dist-info/RECORD
