Metadata-Version: 2.1
Name: sanysdk
Version: 0.0.4
Summary: Encapsulateing Interface
Home-page: https://gitlab.sanywind.net/bigdata/dmo-client-python-sdk
Author: liuxb
Author-email: llxiangbin@163.com
License: MIT Licence
Keywords: pip,sanysdk,liuxb,sdk,sany
Platform: any
License-File: LICENSE
Requires-Dist: requests
Requires-Dist: pandas
Requires-Dist: retry
